zohodb/__init__.py
zohodb/zohodb.py
zohodb.py-1.0.4.dist-info/LICENSE.txt
zohodb.py-1.0.4.dist-info/METADATA
zohodb.py-1.0.4.dist-info/WHEEL
zohodb.py-1.0.4.dist-info/top_level.txt
zohodb.py-1.0.4.dist-info/RECORD
