Metadata-Version: 2.1
Name: zohodb.py
Version: 1.0.4
Summary: Use Zoho Sheets as a database server
Home-page: https://github.com/oddmario/zohodb.py
Author: Mario
Author-email: mariolatif741@yandex.com
License: GNU GPLv3
Keywords: zohodb.py,zohodb,database,zoho,sheets
Platform: UNKNOWN
License-File: LICENSE.txt
Requires-Dist: httpx
